LICENSE
MANIFEST.in
README.md
requirements.txt
setup.py
bin/edgelist_to_clusters.py
niche_space.egg-info/PKG-INFO
niche_space.egg-info/SOURCES.txt
niche_space.egg-info/dependency_links.txt
niche_space.egg-info/requires.txt
niche_space.egg-info/top_level.txt
nichespace/__init__.py
nichespace/llm.py
nichespace/manifold.py
nichespace/neighbors.py
nichespace/utils.py