Metadata-Version: 2.4
Name: niche-space
Version: 2025.3.14
Summary: Hierarchical niche space analysis in python
Home-page: https://github.com/jolespin/niche-space
Author: Josh L. Espinoza
License: MIT
Classifier: Programming Language :: Python :: 3
Classifier: License :: OSI Approved :: MIT License
Classifier: Operating System :: OS Independent
Requires-Python: >=3.6
License-File: LICENSE
Requires-Dist: numpy>=1.9
Requires-Dist: scipy>=1.11
Requires-Dist: pandas
Requires-Dist: scikit-learn<=1.3.0,>=1.2.1
Requires-Dist: tqdm
Requires-Dist: memory_profiler
Requires-Dist: pyexeggutor>=2025.2.19
Requires-Dist: datafold>=2.0.1
Requires-Dist: clairvoyance-feature-selection>=2025.2.21.post2
Requires-Dist: pacmap
Requires-Dist: networkx
Requires-Dist: igraph
Requires-Dist: ensemble_networkx>=2025.3.4.post1
Requires-Dist: optuna
Requires-Dist: fastparquet
Requires-Dist: xarray
Requires-Dist: h5netcdf
Requires-Dist: anndata
Dynamic: author
Dynamic: classifier
Dynamic: description
Dynamic: description-content-type
Dynamic: home-page
Dynamic: license
Dynamic: license-file
Dynamic: requires-dist
Dynamic: requires-python
Dynamic: summary
